{"users":[
	{
		"name": "lucas",
		"age": "36",
		"thumb": "https://avatar.iran.liara.run/public/20"
	},
	{
		"name": "mariana",
		"age": "28",
		"thumb": "https://images.app.goo.gl/nyRsDQZQ6e2i2jF38"
	},
	{
		"name": "daniel",
		"age": "26",
		"thumb": "https://images.app.goo.gl/nyRsDQZQ6e2i2jF38"
	},
	{
		"name": "giovana",
		"age": "24",
		"thumb": "https://images.app.goo.gl/nyRsDQZQ6e2i2jF38"
	},
	{
		"name": "rafael",
		"age": "32",
		"thumb": "https://images.app.goo.gl/nyRsDQZQ6e2i2jF38"
	},
	{
		"name": "bruno",
		"age": "40",
		"thumb": "https://images.app.goo.gl/nyRsDQZQ6e2i2jF38"
	}
]
}
